[
    {
        "name": "Команда Shelfy (стартап)",
        "position": "Frontend Developer (Team Lead)",
        "workURL": "",
        "usedDevTools": [
            "vite",
            "html",
            "css",
            "typescript",
            "react",
            "react-router",
            "redux",
            "scss",
            "adobe-photoshop",
            "figma"
        ],
        "description": "Мы - молодая команда, работающая над платформой для поиска, отслеживания и управления информацией о мультимедийных продуктах, таких как игры, фильмы, сериалы и книги. Наша цель - создать удобный инструмент, который позволит пользователям отслеживать контент, который они просмотрели, прочитали или дополнили, открывать для себя новые продукты с помощью персонализированных рекомендаций и взаимодействовать с друзьями с помощью социальных функций (лента активности, система друзей, совместный выбор продуктов и т.д.).",
        "dateStart": "Сентябрь 2024",
        "dateEnd": "Настоящее"
    }
]
